caprotoapps/__init__.py
caprotoapps/alive.py
caprotoapps/exceptions.py
caprotoapps/manager.py
caprotoapps/examples/__init__.py
caprotoapps/examples/labjack_ioc.py
caprotoapps/labjack/__init__.py
caprotoapps/labjack/driver.py
caprotoapps/labjack/ioc.py
caprotoapps/labjack/tests/test_driver.py
caprotoapps/labjack/tests/test_ioc.py
caproto_apps-0.3.0.dist-info/LICENSE
caproto_apps-0.3.0.dist-info/METADATA
caproto_apps-0.3.0.dist-info/WHEEL
caproto_apps-0.3.0.dist-info/top_level.txt
caproto_apps-0.3.0.dist-info/RECORD
